json_include.py
exabyte_json_include-2023.12.23.post0.dist-info/METADATA
exabyte_json_include-2023.12.23.post0.dist-info/WHEEL
exabyte_json_include-2023.12.23.post0.dist-info/top_level.txt
exabyte_json_include-2023.12.23.post0.dist-info/RECORD
