Metadata-Version: 2.1
Name: exabyte-json-include
Version: 2023.12.23.post0
Summary: An extension for json_include to support file inclusion
Home-page: https://github.com/Exabyte-io/json_include
Author: Exabyte Inc.
Author-email: info@exabyte.io
Classifier: Programming Language :: Python
Classifier: Development Status :: 3 - Alpha
Classifier: Intended Audience :: Developers
Classifier: Topic :: Software Development
Requires-Python: >=3.6
Provides-Extra: test
Requires-Dist: coverage[toml] >=5.3 ; extra == 'test'
